package_made_by_umer/__init__.py
package_made_by_umer/module_one.py
package_made_by_umer/module_two.py
package_made_by_umer-0.1.0.dist-info/METADATA
package_made_by_umer-0.1.0.dist-info/WHEEL
package_made_by_umer-0.1.0.dist-info/top_level.txt
package_made_by_umer-0.1.0.dist-info/RECORD
