Metadata-Version: 2.1
Name: package_made_by_umer
Version: 0.1.0
Summary: Core machine learning code for platform integration.
Author: M Umer Sohail Khan
Author-email: umerpythondevelopment@example.com
Classifier: Programming Language :: Python :: 3
Classifier: License :: OSI Approved :: MIT License
Classifier: Operating System :: OS Independent
Requires-Python: >=3.6
Requires-Dist: numpy>=1.21.0
Requires-Dist: pandas>=1.3.0
